autorelease/__init__.py
autorelease/__main__.py
autorelease/common.py
autorelease/github.py
autorelease/kokoro.py
autorelease/report.xml.j2
autorelease/reporter.py
autorelease/tag.py
autorelease/trigger.py
gcp_releasetool-2.6.1.dist-info/licenses/LICENSE
protos/__init__.py
protos/kokoro_api_pb2.py
releasetool/__init__.py
releasetool/__main__.py
releasetool/circleci.py
releasetool/filehelpers.py
releasetool/git.py
releasetool/github.py
releasetool/secrets.py
releasetool/update_check.py
releasetool/commands/__init__.py
releasetool/commands/common.py
releasetool/commands/publish_reporter.py
releasetool/commands/publish_reporter.sh
releasetool/commands/start/__init__.py
releasetool/commands/start/go.py
releasetool/commands/start/java.py
releasetool/commands/start/nodejs.py
releasetool/commands/start/python.py
releasetool/commands/start/python_tool.py
releasetool/commands/start/ruby.py
releasetool/commands/tag/__init__.py
releasetool/commands/tag/cpp.py
releasetool/commands/tag/dotnet.py
releasetool/commands/tag/go.py
releasetool/commands/tag/java.py
releasetool/commands/tag/nodejs.py
releasetool/commands/tag/php.py
releasetool/commands/tag/python.py
releasetool/commands/tag/python_tool.py
releasetool/commands/tag/ruby.py
tests/__init__.py
tests/common_test.py
tests/test_autorelease_tag.py
tests/test_autorelease_trigger.py
tests/test_dummy.py
tests/test_github.py
tests/test_publish_reporter.py
gcp_releasetool-2.6.1.dist-info/METADATA
gcp_releasetool-2.6.1.dist-info/WHEEL
gcp_releasetool-2.6.1.dist-info/entry_points.txt
gcp_releasetool-2.6.1.dist-info/top_level.txt
gcp_releasetool-2.6.1.dist-info/RECORD
