Metadata-Version: 2.4
Name: gcp-releasetool
Version: 2.6.1
Home-page: 
Author: Google LLC
Author-email: theaflowers@google.com
License: Apache 2.0
Platform: Posix; MacOS X; Windows
Classifier: Development Status :: 3 - Alpha
Classifier: Intended Audience :: Developers
Classifier: License :: OSI Approved :: Apache Software License
Classifier: Programming Language :: Python
Classifier: Programming Language :: Python :: 3.8
Classifier: Programming Language :: Python :: 3.9
Classifier: Programming Language :: Python :: 3.10
Classifier: Programming Language :: Python :: 3.11
Classifier: Programming Language :: Python :: 3.12
Classifier: Operating System :: OS Independent
Classifier: Topic :: Internet
Requires-Python: >=3.8
License-File: LICENSE
Requires-Dist: requests>=2.31.0
Requires-Dist: attrs>=20.1.0
Requires-Dist: click<8.1.0,>=8.0.4
Requires-Dist: cryptography>=42
Requires-Dist: google-auth>=2.22.0
Requires-Dist: jinja2>=3.1.3
Requires-Dist: keyring>=21.8.0
Requires-Dist: packaging>=20.0
Requires-Dist: protobuf>=4.21.6
Requires-Dist: pyjwt>=2.0.0
Requires-Dist: pyperclip>=1.8.0
Requires-Dist: python-dateutil>=2.8.1
Dynamic: author
Dynamic: author-email
Dynamic: classifier
Dynamic: license
Dynamic: license-file
Dynamic: platform
Dynamic: requires-dist
Dynamic: requires-python
